pytorchext/__init__.py
pytorchext/data/__init__.py
pytorchext/data/datasets/TimeseriesDataset.py
pytorchext/data/datasets/__init__.py
pytorchext-0.0.1.post1.dist-info/LICENSE
pytorchext-0.0.1.post1.dist-info/METADATA
pytorchext-0.0.1.post1.dist-info/WHEEL
pytorchext-0.0.1.post1.dist-info/top_level.txt
pytorchext-0.0.1.post1.dist-info/RECORD
